{
    "1": {
        "authors": null,
        "changes": [],
        "comments": "A ver que pedazo de comentarios",
        "date_init": "2023-07-6",
        "description": "A ver que pedazo de descripcion",
        "estability": 2,
        "id": {
            "id": 1,
            "prefix": "NF"
        },
        "importanceLevel": 3,
        "name": "A ver que pedazo de texto",
        "phase": 6,
        "tracesFrom": [
            {
                "id": 2,
                "prefix": "UC"
            }
        ],
        "tracesTo": [
            {
                "id": 1,
                "prefix": "SH"
            },
            {
                "id": 1,
                "prefix": "UC"
            }
        ],
        "urgencyLevel": 3,
        "versionMajor": "1",
        "versionMinor": "0"
    }
}
